{"key":"group_5ba8506ea7316__trashed","title":"Donation Pages Settings","fields":[{"key":"field_5ba8509630437","label":"About Judicial Watch Donations","name":"about_judicial_watch_donations","type":"wysiwyg","instructions":"This text will appear on every donation page.","required":0,"conditional_logic":0,"wrapper":{"width":"","class":"","id":""},"default_value":"","tabs":"all","toolbar":"full","media_upload":1,"delay":0},{"key":"field_5ba8511730438","label":"Contact Button Destination","name":"contact_button_destination","type":"url","instructions":"This is where the contact button will direct to on every donation page.","required":0,"conditional_logic":0,"wrapper":{"width":"","class":"","id":""},"default_value":"","placeholder":""}],"location":[[{"param":"post","operator":"==","value":"1"}]],"menu_order":0,"position":"normal","style":"default","label_placement":"top","instruction_placement":"label","hide_on_screen":"","active":0,"description":""}